excel_dropdown/__init__.py
excel_dropdown/cli.py
excel_dropdown/utils.py
excel_dropdown_tool-1.0.1.dist-info/LICENSE
excel_dropdown_tool-1.0.1.dist-info/METADATA
excel_dropdown_tool-1.0.1.dist-info/WHEEL
excel_dropdown_tool-1.0.1.dist-info/entry_points.txt
excel_dropdown_tool-1.0.1.dist-info/top_level.txt
excel_dropdown_tool-1.0.1.dist-info/RECORD
