Metadata-Version: 2.2
Name: excel-dropdown-tool
Version: 1.0.1
Summary: Excel file processor with dynamic dropdown creation
Home-page: https://github.com/romin23/automate-excel-data-validation
Author: Romin Katre
Author-email: romin.katre32.rk@gmail.com
License: MIT
Keywords: excel dropdown automation openpyxl xlsxwriter
Classifier: Programming Language :: Python :: 3
Classifier: License :: OSI Approved :: MIT License
Classifier: Operating System :: OS Independent
Classifier: Intended Audience :: Developers
Classifier: Topic :: Office/Business :: Financial :: Spreadsheet
Classifier: Topic :: Software Development :: Libraries :: Python Modules
Requires-Python: >=3.6
License-File: LICENSE
Requires-Dist: numpy==2.2.3
Requires-Dist: openpyxl==3.1.5
Requires-Dist: pandas==2.2.3
Requires-Dist: python-dateutil==2.9.0.post0
Requires-Dist: pytz==2025.1
Requires-Dist: six==1.17.0
Requires-Dist: tzdata==2025.1
Requires-Dist: XlsxWriter==3.2.2
Requires-Dist: et_xmlfile==2.0.0
Requires-Dist: tqdm==4.67.1
Dynamic: author
Dynamic: author-email
Dynamic: classifier
Dynamic: description
Dynamic: description-content-type
Dynamic: home-page
Dynamic: keywords
Dynamic: license
Dynamic: requires-dist
Dynamic: requires-python
Dynamic: summary
